denarius
