Metadata-Version: 1.0
Name: denarius
Version: 2018.4.16.1225
Summary: currency and other utilities
Home-page: https://github.com/wdbm/denarius
Author: Will Breaden Madden
Author-email: wbm@protonmail.ch
License: GPLv3
Platform: UNKNOWN
